{
  "_comment": "Hand-curated phrases merged into PHRASE_DICT ahead of the HSK word list. Use this file to add common phrases HSK 3.0 omits (e.g. greetings). Re-run scripts/build-dictionary.mts after editing.",
  "phrases": {
    "你好": "hello",
    "谢谢": "thank you",
    "再见": "goodbye",
    "对不起": "sorry",
    "没关系": "it's okay",
    "不客气": "you're welcome",
    "早上好": "good morning",
    "晚上好": "good evening",
    "晚安": "good night",
    "我爱你": "I love you",
    "中国": "China",
    "美国": "America",
    "朋友": "friend",
    "学生": "student",
    "老师": "teacher",
    "大学": "university",
    "学校": "school",
    "工作": "work",
    "电话": "telephone",
    "电脑": "computer",
    "手机": "cellphone",
    "今天": "today",
    "明天": "tomorrow",
    "昨天": "yesterday",
    "吃饭": "eat",
    "喝水": "drink water",
    "睡觉": "sleep",
    "看书": "read a book",
    "什么": "what",
    "怎么": "how",
    "为什么": "why",
    "多少": "how much",
    "漂亮": "beautiful",
    "高兴": "happy",
    "快乐": "happy",
    "开心": "happy",
    "好吃": "delicious",
    "可以": "can/may",
    "知道": "know",
    "喜欢": "like",
    "非常": "very much",
    "一起": "together",
    "时候": "time/when",
    "现在": "now",
    "以后": "later",
    "以前": "before",
    "已经": "already",
    "还是": "or/still",
    "但是": "but",
    "因为": "because",
    "所以": "so/therefore",
    "如果": "if",
    "虽然": "although",
    "可能": "maybe",
    "应该": "should",
    "需要": "need",
    "希望": "hope",
    "觉得": "feel/think",
    "认为": "think/believe",
    "帮助": "help",
    "问题": "question",
    "回答": "answer",
    "生活": "life",
    "东西": "thing",
    "地方": "place",
    "身体": "body",
    "天气": "weather",
    "中文": "Chinese language",
    "英文": "English language",
    "练习": "practice",
    "汉字": "Chinese character"
  }
}
